py_graspi/__init__.py
py_graspi/descriptors.py
py_graspi/graph.py
py_graspi/graph_data_class.py
py_graspi-0.2.1.2.dist-info/licenses/LICENSE
py_graspi-0.2.1.2.dist-info/METADATA
py_graspi-0.2.1.2.dist-info/WHEEL
py_graspi-0.2.1.2.dist-info/top_level.txt
py_graspi-0.2.1.2.dist-info/RECORD
